access_py_telemetry/__init__.py
access_py_telemetry/_version.py
access_py_telemetry/api.py
access_py_telemetry/ast.py
access_py_telemetry/cli.py
access_py_telemetry/config.yaml
access_py_telemetry/decorators.py
access_py_telemetry/registry.py
access_py_telemetry/utils.py
access_py_telemetry/templates/telemetry_template.py
access_py_telemetry-0.1.9.dist-info/licenses/AUTHORS.rst
access_py_telemetry-0.1.9.dist-info/licenses/LICENSE
access_py_telemetry-0.1.9.dist-info/METADATA
access_py_telemetry-0.1.9.dist-info/WHEEL
access_py_telemetry-0.1.9.dist-info/entry_points.txt
access_py_telemetry-0.1.9.dist-info/top_level.txt
access_py_telemetry-0.1.9.dist-info/RECORD
