Metadata-Version: 2.4
Name: access_py_telemetry
Version: 0.1.9
Summary: Contains ipython extensions to automatically add telemetry to registered function calls from Ipython kernels
Author: ACCESS-NRI
Maintainer: ACCESS-NRI
License: Apache Software License 2.0
Project-URL: bugs, https://github.com/ACCESS-NRI/access-py-telemetry/issues
Project-URL: changelog, https://github.com/ACCESS-NRI/access-py-telemetry/blob/main/CHANGELOG.md
Project-URL: homepage, https://github.com/ACCESS-NRI/access-py-telemetry
Classifier: Development Status :: 4 - Beta
Classifier: Programming Language :: Python :: 3
Classifier: License :: OSI Approved :: Apache Software License
Classifier: Operating System :: OS Independent
Requires-Python: >=3.10
License-File: LICENSE
License-File: AUTHORS.rst
Requires-Dist: ipython>=7.0.0
Requires-Dist: pydantic>=2.0.0
Requires-Dist: pyyaml>=6.0.0
Requires-Dist: httpx>=0.28.0
Provides-Extra: dev
Requires-Dist: coverage; extra == "dev"
Requires-Dist: mypy; extra == "dev"
Requires-Dist: pytest; extra == "dev"
Requires-Dist: ruff; extra == "dev"
Requires-Dist: pytest-httpserver; extra == "dev"
Requires-Dist: intake; extra == "dev"
Requires-Dist: access-nri-intake; extra == "dev"
Requires-Dist: numpy; extra == "dev"
Dynamic: license-file
